{
    "id": 40,
    "title": "Benets Cafe",
    "slug": "benets-cafe",
    "description": "Due to the implications of COVID-19 Spacefinder is currently being used primarily to provide information on library spaces in Cambridge. Filter search by 'I want to work in a library' to isolate these spaces. The information below is likely to be inaccurate, please contact the company direct regarding their current access arrangements.",
    "access": "Anyone (public)",
    "space_type": "Café",
    "address": "21, King's Parade, Cambridge, CB2 1SP",
    "building": "",
    "restricted": true,
    "restriction": "Please contact the company direct regarding their current access arrangements.",
    "disabled_access": false,
    "url": "https://plus.google.com/104830534335234164556/about?gl=uk&hl=en",
    "phone_number": "01223 329068",
    "twitter_screen_name": "",
    "facebook_url": "",
    "campusmap_url": "",
    "campusmap_ref": "",
    "booking_url": "",
    "noise": "Background chatter",
    "atmosphere": [
        "disciplined",
        "social",
        "friendly"
    ],
    "facilities": [
        "food_drink",
        "daylight",
        "views",
        "no_wifi",
        "laptops_allowed",
        "signal",
        "outdoor_seating",
        "toilets",
        "refreshments",
        "break"
    ],
    "work": [
        "private"
    ],
    "tags": [
        "coffee",
        "food and drink",
        "warm",
        "no wifi",
        "central"
    ],
    "floor": "",
    "image": "benets.jpg",
    "location": "{\"type\":\"Point\",\"coordinates\":[\"0.117845\",\"52.204979\"]}",
    "opening_hours": {
        "monday": {
            "open": true,
            "from": "8:30",
            "to": "22:00"
        },
        "tuesday": {
            "open": true,
            "from": "8:30",
            "to": "22:00"
        },
        "wednesday": {
            "open": true,
            "from": "8:30",
            "to": "22:00"
        },
        "thursday": {
            "open": true,
            "from": "8:30",
            "to": "22:00"
        },
        "friday": {
            "open": true,
            "from": "8:30",
            "to": "22:00"
        },
        "saturday": {
            "open": true,
            "from": "8:30",
            "to": "22:00"
        },
        "sunday": {
            "open": true,
            "from": "8:30",
            "to": "22:00"
        }
    }
}